streamlit_script/__init__.py
streamlit_script/__main__.py
streamlit_script-0.2.2.dist-info/entry_points.txt
streamlit_script-0.2.2.dist-info/METADATA
streamlit_script-0.2.2.dist-info/WHEEL
streamlit_script-0.2.2.dist-info/RECORD
